setup.py
CorePost.egg-info/PKG-INFO
CorePost.egg-info/SOURCES.txt
CorePost.egg-info/dependency_links.txt
CorePost.egg-info/requires.txt
CorePost.egg-info/top_level.txt
CorePost.egg-info/zip-safe
corepost/__init__.py
corepost/convert.py
corepost/enums.py
corepost/filters.py
corepost/routing.py
corepost/security.py
corepost/utils.py
corepost/web.py