Metadata-Version: 1.1
Name: CorePost
Version: 0.0.15
Summary: A Twisted Web REST micro-framework
Home-page: https://github.com/jacek99/corepost
Author: Jacek Furmankiewicz
Author-email: jacek99@gmail.com
License: BSD
Keywords: twisted rest flask sinatra get post put delete web
Platform: UNKNOWN
Classifier: Development Status :: 3 - Alpha
Classifier: Environment :: Web Environment
Classifier: Intended Audience :: Developers
Classifier: License :: OSI Approved :: BSD License
Classifier: Operating System :: OS Independent
Classifier: Programming Language :: Python
Classifier: Topic :: Internet :: WWW/HTTP :: Dynamic Content
Classifier: Topic :: Software Development :: Libraries :: Python Modules
